Metadata-Version: 2.1
Name: pyscord
Version: 0.0.0.dev0
Summary: Discord API wrapper rebuild from scratch.
Home-page: https://github.com/Pyscord/Pyscord
Author: Sigmanificient, Arthurdw
Author-email: contact@pyscord.org
License: MIT
Project-URL: Github repository, https://github.com/Pyscord/pyscord
Keywords: discord,api,asynchronous
Platform: UNKNOWN
Classifier: Development Status :: 1 - Planning
Classifier: Intended Audience :: Developers
Classifier: Topic :: Software Development :: Build Tools
Classifier: License :: OSI Approved :: MIT License
Classifier: Programming Language :: Python :: 3.6
Classifier: Programming Language :: Python :: 3.7
Classifier: Programming Language :: Python :: 3.8
Classifier: Programming Language :: Python :: 3.9
License-File: LICENSE
